odbc2deltalake/__init__.py
odbc2deltalake/consistency.py
odbc2deltalake/db_to_delta.py
odbc2deltalake/delta_logger.py
odbc2deltalake/load_infos.py
odbc2deltalake/load_result.py
odbc2deltalake/logging.py
odbc2deltalake/metadata.py
odbc2deltalake/odbc_utils.py
odbc2deltalake/query.py
odbc2deltalake/sql_glot_utils.py
odbc2deltalake/sql_schema.py
odbc2deltalake/utils.py
odbc2deltalake/write_init.py
odbc2deltalake/destination/__init__.py
odbc2deltalake/destination/azure.py
odbc2deltalake/destination/azure_utils.py
odbc2deltalake/destination/databricks.py
odbc2deltalake/destination/destination.py
odbc2deltalake/destination/file_system.py
odbc2deltalake/read_utils/delta_rs.py
odbc2deltalake/reader/__init__.py
odbc2deltalake/reader/adbc_reader.py
odbc2deltalake/reader/odbc_reader.py
odbc2deltalake/reader/reader.py
odbc2deltalake/reader/spark_reader.py
odbc2deltalake/write_utils/__init__.py
odbc2deltalake/write_utils/restore_pk.py
odbc2deltalake-0.14.1.dist-info/METADATA
odbc2deltalake-0.14.1.dist-info/WHEEL
odbc2deltalake-0.14.1.dist-info/licenses/LICENSE
odbc2deltalake-0.14.1.dist-info/RECORD
