Metadata-Version: 2.4
Name: odbc2deltalake
Version: 0.14.1
Author-email: Adrian Ehrsam <adrian.ehrsam@bmsuisse.ch>
License-File: LICENSE
Requires-Python: ~=3.9
Requires-Dist: azure-identity<2,>=1.15.0
Requires-Dist: pydantic>=1.10.0
Requires-Dist: sqlglot>=23.17.0
Provides-Extra: adbc
Requires-Dist: adbc-driver-manager>=1.7.0; extra == 'adbc'
Provides-Extra: local
Requires-Dist: arrow-odbc; extra == 'local'
Requires-Dist: arrow-odbc>=5.0.0; extra == 'local'
Requires-Dist: deltalake; extra == 'local'
Requires-Dist: deltalake2db[deltalake]>=0.9.3; extra == 'local'
Requires-Dist: deltalake>=0.17.1; extra == 'local'
Requires-Dist: duckdb; extra == 'local'
Requires-Dist: pyarrow>=16.1; extra == 'local'
Requires-Dist: pyodbc<6,>=5.1.0; extra == 'local'
Provides-Extra: local-azure
Requires-Dist: adlfs; extra == 'local-azure'
Requires-Dist: adlfs<2025,>=2024.2.0; extra == 'local-azure'
Requires-Dist: arrow-odbc>=5.0.0; extra == 'local-azure'
Requires-Dist: azure-identity; extra == 'local-azure'
Requires-Dist: azure-storage-file-datalake; extra == 'local-azure'
Requires-Dist: deltalake2db[deltalake]>=0.9.3; extra == 'local-azure'
Requires-Dist: deltalake>=0.17.1; extra == 'local-azure'
Requires-Dist: pyarrow>=16.1; extra == 'local-azure'
Requires-Dist: pyodbc<6,>=5.1.0; extra == 'local-azure'
Provides-Extra: mssql
Requires-Dist: pyodbc<6,>=5.1.0; extra == 'mssql'
Provides-Extra: postgres
Requires-Dist: adbc-driver-postgresql>=1.7.0; extra == 'postgres'
